[
  {
    "name": "ai.djl.repository.zoo.DefaultZooProvider",
    "allDeclaredConstructors": true,
    "allPublicConstructors": true,
    "allDeclaredMethods": true,
    "allPublicMethods": true
  },
  {
    "name": "ai.djl.modality.cv.BufferedImageFactory",
    "allDeclaredConstructors": true,
    "allPublicConstructors": true,
    "allDeclaredMethods": true,
    "allPublicMethods": true
  },
  {
    "name": "ai.djl.repository.Metadata",
    "allDeclaredFields": true,
    "allDeclaredConstructors": true,
    "allPublicConstructors": true,
    "allDeclaredMethods": true,
    "allPublicMethods": true
  },
  {
    "name": "ai.djl.repository.License",
    "allDeclaredFields": true,
    "allDeclaredConstructors": true,
    "allPublicConstructors": true,
    "allDeclaredMethods": true,
    "allPublicMethods": true
  },
  {
    "name": "ai.djl.repository.Artifact",
    "allDeclaredFields": true,
    "allDeclaredConstructors": true,
    "allPublicConstructors": true,
    "allDeclaredMethods": true,
    "allPublicMethods": true
  },
  {
    "name": "ai.djl.repository.Artifact$Item",
    "allDeclaredFields": true,
    "allDeclaredConstructors": true,
    "allPublicConstructors": true,
    "allDeclaredMethods": true,
    "allPublicMethods": true
  },
  {
    "name": "ai.djl.repository.Version",
    "allDeclaredFields": true,
    "allDeclaredConstructors": true,
    "allPublicConstructors": true,
    "allDeclaredMethods": true,
    "allPublicMethods": true
  }
]
